setup.py
snippetconvertor/__init__.py
snippetconvertor/snippetconv.py
snippetconvertor.egg-info/PKG-INFO
snippetconvertor.egg-info/SOURCES.txt
snippetconvertor.egg-info/dependency_links.txt
snippetconvertor.egg-info/top_level.txt