Metadata-Version: 2.1
Name: snippetconvertor
Version: 0.0.3
Summary: VScode  snippet & Eclipse Template convertor
Author: AndyZhu
Author-email: andyzhu@live.com
